did/__init__.py
did/blockchain.py
did/constants.py
did/did.py
did/encryptor.py
did/enums.py
did/keys.py
did/models.py
did/service.py
did/updater.py
factom_did/__init__.py
factom_did/client/__init__.py
factom_did/client/blockchain.py
factom_did/client/constants.py
factom_did/client/deactivator.py
factom_did/client/did.py
factom_did/client/encryptor.py
factom_did/client/enums.py
factom_did/client/service.py
factom_did/client/updater.py
factom_did/client/validators.py
factom_did/client/version_upgrader.py
factom_did/client/keys/__init__.py
factom_did/client/keys/abstract.py
factom_did/client/keys/did.py
factom_did/client/keys/ecdsa.py
factom_did/client/keys/eddsa.py
factom_did/client/keys/management.py
factom_did/client/keys/rsa.py
factom_did/resolver/__init__.py
factom_did/resolver/entry_processors.py
factom_did/resolver/exceptions.py
factom_did/resolver/parser.py
factom_did/resolver/schema.py
factom_did/resolver/validators.py
tests/client/__init__.py
tests/client/test_deactivator.py
tests/client/test_did.py
tests/client/test_encryptor.py
tests/client/test_service.py
tests/client/test_updater.py
tests/client/test_version_upgrader.py
tests/client/keys/__init__.py
tests/client/keys/test_abstract.py
tests/client/keys/test_did.py
tests/client/keys/test_management.py
tests/client/keys/test_rsa.py
tests/resolver/__init__.py
tests/resolver/test_parser.py
tests/resolver/test_validators.py
py_factom_did-0.5.0.dist-info/LICENSE
py_factom_did-0.5.0.dist-info/METADATA
py_factom_did-0.5.0.dist-info/WHEEL
py_factom_did-0.5.0.dist-info/top_level.txt
py_factom_did-0.5.0.dist-info/RECORD
