Metadata-Version: 2.1
Name: py-factom-did
Version: 0.5.0
Summary: Python library for Factom DIDs
Home-page: https://github.com/factomatic/py-factom-did
Author: Peter Asenov, Valentin Ganev
Author-email: info@factomatic.io
License: MIT License
Platform: OS Independent
Classifier: Development Status :: 4 - Beta
Classifier: Intended Audience :: Developers
Classifier: License :: OSI Approved :: MIT License
Classifier: Operating System :: OS Independent
Classifier: Programming Language :: Python :: 3.6
Classifier: Programming Language :: Python :: 3.7
Classifier: Topic :: Internet :: WWW/HTTP
Classifier: Topic :: Security
Classifier: Topic :: Security :: Cryptography
Classifier: Topic :: Software Development
Requires-Python: >=3.6
Requires-Dist: base58 (>=1.0.3)
Requires-Dist: ecdsa (>=0.13.2)
Requires-Dist: ed25519 (>=1.5)
Requires-Dist: factom-api (>=1.0.2)
Requires-Dist: pycryptodome (>=3.9.0)
